{
  "main": {
    "id": "a45455adc998327a",
    "type": "split",
    "children": [
      {
        "id": "0ed8c0e235ff9158",
        "type": "tabs",
        "children": [
          {
            "id": "1bda17ae67bd476e",
            "type": "leaf",
            "state": {
              "type": "markdown",
              "state": {
                "file": "1) 02-26 - Introduction.md",
                "mode": "source",
                "source": false
              },
              "icon": "lucide-file",
              "title": "1) 02-26 - Introduction"
            }
          },
          {
            "id": "45fcb59e9d56d6a1",
            "type": "leaf",
            "state": {
              "type": "markdown",
              "state": {
                "file": "3) Experimental methodology in natural language precessing.md",
                "mode": "source",
                "source": false
              },
              "icon": "lucide-file",
              "title": "3) Experimental methodology in natural language precessing"
            }
          }
        ],
        "currentTab": 1
      }
    ],
    "direction": "vertical"
  },
  "left": {
    "id": "c827cb974339f515",
    "type": "split",
    "children": [
      {
        "id": "dab303c36a26cb34",
        "type": "tabs",
        "children": [
          {
            "id": "0957d7fc31c47b16",
            "type": "leaf",
            "state": {
              "type": "file-explorer",
              "state": {
                "sortOrder": "alphabetical",
                "autoReveal": false
              },
              "icon": "lucide-folder-closed",
              "title": "Files"
            }
          },
          {
            "id": "aacd8d157c18c700",
            "type": "leaf",
            "state": {
              "type": "search",
              "state": {
                "query": "",
                "matchingCase": false,
                "explainSearch": false,
                "collapseAll": false,
                "extraContext": false,
                "sortOrder": "alphabetical"
              },
              "icon": "lucide-search",
              "title": "Search"
            }
          },
          {
            "id": "38d310e2ef118a2c",
            "type": "leaf",
            "state": {
              "type": "bookmarks",
              "state": {},
              "icon": "lucide-bookmark",
              "title": "Bookmarks"
            }
          }
        ]
      }
    ],
    "direction": "horizontal",
    "width": 300
  },
  "right": {
    "id": "d0b6173604c30e4a",
    "type": "split",
    "children": [
      {
        "id": "c8227c33e335d423",
        "type": "tabs",
        "children": [
          {
            "id": "31b5bb1fe0a6ab40",
            "type": "leaf",
            "state": {
              "type": "backlink",
              "state": {
                "file": "1) 02-26 - Introduction.md",
                "collapseAll": false,
                "extraContext": false,
                "sortOrder": "alphabetical",
                "showSearch": false,
                "searchQuery": "",
                "backlinkCollapsed": false,
                "unlinkedCollapsed": true
              },
              "icon": "links-coming-in",
              "title": "Backlinks for 1) 02-26 - Introduction"
            }
          },
          {
            "id": "b76c106a563d1076",
            "type": "leaf",
            "state": {
              "type": "outgoing-link",
              "state": {
                "file": "1) 02-26 - Introduction.md",
                "linksCollapsed": false,
                "unlinkedCollapsed": true
              },
              "icon": "links-going-out",
              "title": "Outgoing links from 1) 02-26 - Introduction"
            }
          },
          {
            "id": "58f3963dd8d53107",
            "type": "leaf",
            "state": {
              "type": "tag",
              "state": {
                "sortOrder": "frequency",
                "useHierarchy": true,
                "showSearch": false,
                "searchQuery": ""
              },
              "icon": "lucide-tags",
              "title": "Tags"
            }
          },
          {
            "id": "424aac646b50d5a4",
            "type": "leaf",
            "state": {
              "type": "all-properties",
              "state": {
                "sortOrder": "frequency",
                "showSearch": false,
                "searchQuery": ""
              },
              "icon": "lucide-archive",
              "title": "All properties"
            }
          },
          {
            "id": "91776efa0be3bc80",
            "type": "leaf",
            "state": {
              "type": "outline",
              "state": {
                "file": "1) 02-26 - Introduction.md",
                "followCursor": false,
                "showSearch": false,
                "searchQuery": ""
              },
              "icon": "lucide-list",
              "title": "Outline of 1) 02-26 - Introduction"
            }
          }
        ]
      }
    ],
    "direction": "horizontal",
    "width": 300,
    "collapsed": true
  },
  "left-ribbon": {
    "hiddenItems": {
      "switcher:Open quick switcher": false,
      "graph:Open graph view": false,
      "canvas:Create new canvas": false,
      "daily-notes:Open today's daily note": false,
      "templates:Insert template": false,
      "command-palette:Open command palette": false,
      "bases:Create new base": false
    }
  },
  "active": "45fcb59e9d56d6a1",
  "lastOpenFiles": [
    "3) Experimental methodology in natural language precessing.md",
    "1) 02-26 - Introduction.md"
  ]
}